[{"n": "30", "Prefix": "quetta", "Symbool": "Q", "Naam": "quintiljoen", "Decimaal": "1000000000000000000000000000000"}, {"n": "-30", "Prefix": "quecto", "Symbool": "q", "Naam": "eenquintiljoenste", "Decimaal": "0.000000000000000000000000000001"}, {"n": "27", "Prefix": "ronna", "Symbool": "R", "Naam": "quadriljard", "Decimaal": "1000000000000000000000000000"}, {"n": "-27", "Prefix": "ronto", "Symbool": "r", "Naam": "eenquadriljardste", "Decimaal": "0.000000000000000000000000001"}, {"n": "24", "Prefix": "yotta", "Symbool": "Y", "Naam": "quadriljoen", "Decimaal": "1000000000000000000000000"}, {"n": "-24", "Prefix": "yocto", "Symbool": "y", "Naam": "eenquadriljoenste", "Decimaal": "0.000000000000000000000001"}, {"n": "21", "Prefix": "zetta", "Symbool": "Z", "Naam": "triljard", "Decimaal": "1000000000000000000000"}, {"n": "-21", "Prefix": "zepto", "Symbool": "z", "Naam": "eentriljardste", "Decimaal": "0.000000000000000000001"}, {"n": "18", "Prefix": "exa", "Symbool": "E", "Naam": "triljoen", "Decimaal": "1000000000000000000"}, {"n": "-18", "Prefix": "atto", "Symbool": "a", "Naam": "eentriljoenste", "Decimaal": "0.000000000000000001"}, {"n": "15", "Prefix": "peta", "Symbool": "P", "Naam": "biljard", "Decimaal": "1000000000000000"}, {"n": "-15", "Prefix": "femto", "Symbool": "f", "Naam": "eenbiljardste", "Decimaal": "0.000000000000001"}, {"n": "12", "Prefix": "tera", "Symbool": "T", "Naam": "biljoen", "Decimaal": "1000000000000"}, {"n": "-12", "Prefix": "pico", "Symbool": "p", "Naam": "eenbiljoenste", "Decimaal": "0.000000000001"}, {"n": "9", "Prefix": "giga", "Symbool": "G", "Naam": "miljard", "Decimaal": "1000000000"}, {"n": "-9", "Prefix": "nano", "Symbool": "n", "Naam": "eenmiljardste", "Decimaal": "0.000000001"}, {"n": "6", "Prefix": "mega", "Symbool": "M", "Naam": "miljoen", "Decimaal": "1000000"}, {"n": "-6", "Prefix": "micro", "Symbool": "\u00b5", "Naam": "eenmiljoenste", "Decimaal": "0.000001"}, {"n": "3", "Prefix": "kilo", "Symbool": "k", "Naam": "duizend", "Decimaal": "1000"}, {"n": "-3", "Prefix": "milli", "Symbool": "m", "Naam": "eenduizendste", "Decimaal": "0.001"}, {"n": "2", "Prefix": "hecto", "Symbool": "h", "Naam": "honderd", "Decimaal": "100"}, {"n": "-2", "Prefix": "centi", "Symbool": "c", "Naam": "eenhonderdste", "Decimaal": "0.01"}, {"n": "1", "Prefix": "deca", "Symbool": "da", "Naam": "tien", "Decimaal": "10"}, {"n": "-1", "Prefix": "deci", "Symbool": "d", "Naam": "eentiende", "Decimaal": "0.1"}]